ultraclick/__init__.py
ultraclick-0.1.1.dist-info/licenses/license.txt
ultraclick-0.1.1.dist-info/METADATA
ultraclick-0.1.1.dist-info/WHEEL
ultraclick-0.1.1.dist-info/top_level.txt
ultraclick-0.1.1.dist-info/RECORD
