Metadata-Version: 2.4
Name: ultraclick
Version: 0.1.1
Summary: Thin wrapper around the Python 'click' library to allow building class based CLIs
Author-email: Ronny Rentner <ultraclick.code@ronny-rentner.de>
Maintainer-email: Ronny Rentner <ultraclick.code@ronny-rentner.de>
License-Expression: GPL-3.0-or-later
Project-URL: Homepage, https://github.com/ronny-rentner/ultraclick
Project-URL: Bug Reports, https://github.com/ronny-rentner/ultraclick/issues
Project-URL: Source, https://github.com/ronny-rentner/ultraclick
Keywords: ultraclick,cli,click,setuptools,development
Classifier: Development Status :: 3 - Alpha
Classifier: Intended Audience :: Developers
Classifier: Topic :: Software Development :: Libraries :: Application Frameworks
Classifier: Topic :: Software Development :: User Interfaces
Classifier: Programming Language :: Python :: 3
Classifier: Programming Language :: Python :: 3.9
Classifier: Programming Language :: Python :: 3.10
Classifier: Programming Language :: Python :: 3.11
Classifier: Programming Language :: Python :: 3.12
Classifier: Programming Language :: Python :: 3.13
Classifier: Programming Language :: Python :: 3 :: Only
Requires-Python: >=3.9
License-File: license.txt
Requires-Dist: click
Requires-Dist: rich
Requires-Dist: rich_click
Provides-Extra: dev
Requires-Dist: check-manifest; extra == "dev"
Provides-Extra: test
Requires-Dist: coverage; extra == "test"
Dynamic: license-file
